{
  "kind": "cloudflare::CustomDomain",
  "id": "abitprojetos.com.br",
  "fqn": "code7sites/projetos/abit/abitprojetos.com.br",
  "seq": 0,
  "data": {},
  "status": "created",
  "output": {
    "Symbol(alchemy::ResourceKind)": "cloudflare::CustomDomain",
    "Symbol(alchemy::ResourceID)": "abitprojetos.com.br",
    "Symbol(alchemy::ResourceFQN)": "code7sites/projetos/abit/abitprojetos.com.br",
    "Symbol(alchemy::ResourceScope)": {
      "@scope": null
    },
    "Symbol(alchemy::ResourceSeq)": 0,
    "name": "abitprojetos.com.br",
    "zoneId": "f9e779b9dfb7735aeb1e13d824f6bdf8",
    "adopt": true,
    "workerName": "code7sites-abit-projetos",
    "dev": false,
    "apiToken": {
      "@secret": {
        "version": "v1",
        "ciphertext": "zIBC/9rFRIcJqv77oK2DqqGVoDLC377HB29/shvaSx4yNKUrL0OmmuSz8/GTmmVSo6AeOOg=",
        "iv": "13nHE+11fAARd86v",
        "salt": "alG0lymfbv4kM9fImqogUQ==",
        "tag": "m27VjAAfDgZiVlFDXNxbaQ=="
      }
    },
    "id": "f531598b7f2844fe66fa394d78ad74a2dacf1841",
    "environment": "production",
    "createdAt": 1777144901445,
    "updatedAt": 1777144901445
  },
  "props": {
    "name": "abitprojetos.com.br",
    "adopt": true,
    "workerName": "code7sites-abit-projetos",
    "dev": false,
    "apiToken": {
      "@secret": {
        "version": "v1",
        "ciphertext": "dx/ADhGLy9m8j2Cs4qDc0wmGxk4c7E7q93rVoW5Sq7bBPh/32F99IROjGFdIsdFhshH9+Ho=",
        "iv": "QYiHWC6XMSGbMV3I",
        "salt": "yNoCiHUqowWu5ukFKQUDtA==",
        "tag": "t+ndqhyH1aO+0zyFU4P9qw=="
      }
    }
  }
}