{
  "kind": "cloudflare::CustomDomain",
  "id": "abitprojetos.com.br",
  "fqn": "code7sites/projetos/abit/abitprojetos.com.br",
  "seq": 0,
  "data": {},
  "status": "created",
  "output": {
    "Symbol(alchemy::ResourceKind)": "cloudflare::CustomDomain",
    "Symbol(alchemy::ResourceID)": "abitprojetos.com.br",
    "Symbol(alchemy::ResourceFQN)": "code7sites/projetos/abit/abitprojetos.com.br",
    "Symbol(alchemy::ResourceScope)": {
      "@scope": null
    },
    "Symbol(alchemy::ResourceSeq)": 0,
    "name": "abitprojetos.com.br",
    "zoneId": "f9e779b9dfb7735aeb1e13d824f6bdf8",
    "adopt": true,
    "workerName": "code7sites-abit-projetos",
    "dev": false,
    "apiToken": {
      "@secret": {
        "version": "v1",
        "ciphertext": "Dfmdf6d09D0Tt9/OIXLQZ/4f4GR/UfbaFB7bL5WLhs2nkjHW25qYKz/6rGomPUuj7C6AHJU=",
        "iv": "PcbPpFRxPgoBLXEN",
        "salt": "e3nRVi+CJ12ZHHCvAx2raA==",
        "tag": "21u3DNIasSDpg6T86D8GKw=="
      }
    },
    "id": "f531598b7f2844fe66fa394d78ad74a2dacf1841",
    "environment": "production",
    "createdAt": 1777083667295,
    "updatedAt": 1777083667295
  },
  "props": {
    "name": "abitprojetos.com.br",
    "adopt": true,
    "workerName": "code7sites-abit-projetos",
    "dev": false,
    "apiToken": {
      "@secret": {
        "version": "v1",
        "ciphertext": "rjabO+hur1UDp0odT0uQpZu0GJbweYzN4+aRGqa3EYIT6UveKBiJeEWBLhWnepg65wh9Ln4=",
        "iv": "pPnW9Revp6EkGIfY",
        "salt": "TV1mktpIxFuYOO0c0gPWkA==",
        "tag": "SkfVs4TMHa0xMtJX+NRPvg=="
      }
    }
  }
}