{
  "kind": "cloudflare::Worker",
  "id": "abit",
  "fqn": "code7sites/projetos/abit",
  "seq": 1,
  "data": {},
  "status": "updated",
  "output": {
    "Symbol(alchemy::ResourceKind)": "cloudflare::Worker",
    "Symbol(alchemy::ResourceID)": "abit",
    "Symbol(alchemy::ResourceFQN)": "code7sites/projetos/abit",
    "Symbol(alchemy::ResourceScope)": {
      "@scope": null
    },
    "Symbol(alchemy::ResourceSeq)": 1,
    "apiToken": {
      "@secret": {
        "version": "v1",
        "ciphertext": "sIr/fYkE8I5rbIaIORCCf4OBvT/YLCik6+4xSECKuz+K8znhRidLb9bpO5OrZHhypPvTEqw=",
        "iv": "ljLG9IPU+YEijx5M",
        "salt": "43Lr91Bod3kf7AfgrPxB8g==",
        "tag": "MDdIvFUbyF1FA5aEBpC/Pw=="
      }
    },
    "domains": [
      {
        "Symbol(alchemy::ResourceKind)": "cloudflare::CustomDomain",
        "Symbol(alchemy::ResourceID)": "abitprojetos.com.br",
        "Symbol(alchemy::ResourceFQN)": "code7sites/projetos/abit/abitprojetos.com.br",
        "Symbol(alchemy::ResourceScope)": {
          "@scope": null
        },
        "Symbol(alchemy::ResourceSeq)": 0,
        "name": "abitprojetos.com.br",
        "zoneId": "f9e779b9dfb7735aeb1e13d824f6bdf8",
        "adopt": true,
        "workerName": "code7sites-abit-projetos",
        "dev": false,
        "apiToken": {
          "@secret": {
            "version": "v1",
            "ciphertext": "nU2nfbn4sK6mQ+Wb8jRtkwEkuOLocrKA47BrXwd1udYAUhJb2UbDMMfP5jwKLW3qw9vHLyc=",
            "iv": "sEgCWVgUfGzQj+nf",
            "salt": "VKF9jqHm0XlPOYsv6Nfpkw==",
            "tag": "zUxRcVoy9LiJe55wUKqbUA=="
          }
        },
        "id": "f531598b7f2844fe66fa394d78ad74a2dacf1841",
        "environment": "production",
        "createdAt": 1777084615876,
        "updatedAt": 1777084615876
      }
    ],
    "noBundle": true,
    "compatibility": "node",
    "entrypoint": ".output/server/index.mjs",
    "name": "code7sites-abit-projetos",
    "cwd": "",
    "compatibilityFlags": [
      "nodejs_compat",
      "nodejs_compat_populate_process_env"
    ],
    "compatibilityDate": "2026-03-10",
    "assets": {
      "html_handling": "auto-trailing-slash",
      "not_found_handling": "single-page-application",
      "run_worker_first": false
    },
    "bindings": {
      "ASSETS": {
        "type": "assets",
        "path": ".output/public"
      }
    },
    "dev": {
      "hasRemote": true
    },
    "type": "service",
    "id": "abit",
    "format": "esm",
    "createdAt": {
      "@date": "2026-04-21T12:43:41.490Z"
    },
    "updatedAt": {
      "@date": "2026-04-25T02:36:55.952Z"
    },
    "url": "https://code7sites-abit-projetos.abitprojetos.workers.dev"
  },
  "props": {
    "apiToken": {
      "@secret": {
        "version": "v1",
        "ciphertext": "fdTPl0gtwABFw8nPoCbB09xsw54GxVLe+45+STwyaDIDBTapDioJ1I5ql45U5tWwkgV2Pas=",
        "iv": "DN18nigV2zDImVAZ",
        "salt": "EiwIi0ComUC0wAqgRj9TPQ==",
        "tag": "EgWp60HBa5KLbVQQ6r1O+A=="
      }
    },
    "domains": [
      "abitprojetos.com.br"
    ],
    "noBundle": true,
    "compatibility": "node",
    "entrypoint": ".output/server/index.mjs",
    "name": "code7sites-abit-projetos",
    "cwd": "",
    "compatibilityFlags": [
      "nodejs_compat",
      "nodejs_compat_populate_process_env"
    ],
    "compatibilityDate": "2026-03-10",
    "assets": {
      "html_handling": "auto-trailing-slash",
      "not_found_handling": "single-page-application",
      "run_worker_first": false
    },
    "bindings": {
      "ASSETS": {
        "type": "assets",
        "path": ".output/public"
      }
    }
  }
}